<?xml version="1.0" encoding="utf-8"?>
<templates xml:space="preserve">
    <t t-name="e_website_design.CatalogDesignComponent">
        <div class="catalog-design-component">
            
            <button class="btn btn-primary filter-toggle-btn" 
                    data-bs-toggle="offcanvas" 
                    data-bs-target="#filterSidebar">
                FILTER
            </button>

            <div class="offcanvas offcanvas-end" id="filterSidebar" tabindex="-1">
                <div class="offcanvas-header">
                    <h5 class="offcanvas-title">Filter</h5>
                    <button type="button" class="btn-close" data-bs-dismiss="offcanvas"></button>
                </div>
                <div class="offcanvas-body">
                    <div class="mb-3">
                        <label class="form-label">Category</label>
                        
                    </div>
                </div>
            </div>

            <div class="container py-3">
                <BreadcrumbComponent back_url="this.back_url" breadcrumbs="this.breadcrumbs"/>
                
                <div class="row g-4 public-design-style mt-3">
                    <t t-foreach="this.state.designs" t-as="design" t-key="design.id">
                        <div class="col-xl-3 col-lg-4 col-md-6 col-sm-12">
                            <div class="card h-100">
                                <img t-if="design.image"
                                    t-attf-src="/web/image/product.design/#{design.id}/image"
                                    class="card-img-top"
                                    t-att-alt="design.name"/>
                                <div t-else="" class="card-img-top d-flex align-items-center justify-content-center bg-light">
                                    <i class="fa fa-image text-muted" style="font-size: 3rem;"></i>
                                </div>
                                <div class="card-body d-flex flex-column">
                                    <h5 class="card-title fw-bold text-truncate">
                                        <t t-esc="design.name"/>
                                    </h5>
                                    <p t-if="design.default_code" class="card-text flex-grow-1 text-muted">
                                        [<t t-esc="design.default_code" t-options='{"widget": "text"}'/>]
                                    </p>
                                </div>
                            </div>
                        </div>
                    </t>
                </div>
            </div>
        </div>
    </t>
</templates>